pmeta/__init__.py
pmeta-0.1.0.dist-info/WHEEL
pmeta-0.1.0.dist-info/METADATA
pmeta-0.1.0.dist-info/RECORD
