Metadata-Version: 2.1
Name: pmeta
Version: 0.1.0
Summary: Python for Meta Analysis
Author: Yajie Zhu
Author-email: yajiez.me@gmail.com
Requires-Python: >=3.7,<4.0
Classifier: Programming Language :: Python :: 3
Classifier: Programming Language :: Python :: 3.7
Classifier: Programming Language :: Python :: 3.8
